uluplot/__init__.py
uluplot/color_dicts.py
uluplot/uluplot.py
uluplot-0.1.0.dist-info/METADATA
uluplot-0.1.0.dist-info/RECORD
uluplot-0.1.0.dist-info/WHEEL
uluplot-0.1.0.dist-info/top_level.txt
