Metadata-Version: 2.1
Name: uluplot
Version: 0.1.0
Summary: Flexible map plot utility based on gmplot
Home-page: http://github.com/ulu5/uluplot
Author: ulu5
Author-email: ulu_5@yahoo.com
License: MIT
Platform: UNKNOWN
Requires-Dist: requests
